{
    "Хабр_": "https://habr.com/ru/",
    "_____________Как_стать_автором___________": "https://habr.com/ru/sandbox/start/",
    "_________Все_потоки_______": "https://habr.com/ru/all/",
    "___________Разработка_________": "https://habr.com/ru/flows/develop/",
    "___________Администрирование_________": "https://habr.com/ru/flows/admin/",
    "___________Дизайн_________": "https://habr.com/ru/flows/design/",
    "___________Менеджмент_________": "https://habr.com/ru/flows/management/",
    "___________Маркетинг_________": "https://habr.com/ru/flows/marketing/",
    "___________Научпоп_________": "https://habr.com/ru/flows/popsci/",
    "Поиск_": "https://habr.com/ru/search/",
    "": "https://habr.com/ru/company/tssolution/profile/",
    "TS_Solution": "https://habr.com/ru/company/tssolution/profile/",
    "_": "https://habr.com/ru/users/vanish0X/",
    "_______vanish0X_______": "https://habr.com/ru/users/vanish0X/",
    "Блог_компании_TS_Solution_": "https://habr.com/ru/company/tssolution/blog/",
    "Информационная_безопасность_*": "https://habr.com/ru/hub/infosecurity/",
    "IT-инфраструктура_*": "https://habr.com/ru/hub/it-infrastructure/",
    "IT-компании_": "https://habr.com/ru/hub/itcompanies/",
    "tssolution.ru/events/positive_187_08_04": "https://tssolution.ru/events/positive_187_08_04",
    "t.me/MPSIEMChat": "https://t.me/MPSIEMChat",
    "Telegram": "https://t.me/tssolution",
    "Facebook": "https://www.facebook.com/groups/tssolution.info/",
    "VK": "https://vk.com/ts_solution",
    "TS_Solution_Blog": "https://tssolution.ru/blog",
    "positive_technologies_ts_solution": "https://habr.com/ru/search/?target_type=posts&order=relevance&q=%5Bpositive%20technologies%20ts%20solution%5D",
    "Блог_компании_TS_Solution": "https://habr.com/ru/company/tssolution/blog/",
    "Информационная_безопасность": "https://habr.com/ru/hub/infosecurity/",
    "IT-инфраструктура": "https://habr.com/ru/hub/it-infrastructure/",
    "IT-компании": "https://habr.com/ru/hub/itcompanies/",
    "Комментарии_________1_____": "https://habr.com/ru/company/tssolution/blog/495280/comments/",
    "_______Сайт_____": "http://tssolution.ru/",
    "___________@vanish0X_________": "https://habr.com/ru/users/vanish0X/",
    "Комментарии__________Комментарии_1______": "https://habr.com/ru/company/tssolution/blog/495280/comments/",
    "_______tssolution.ru_____": "http://tssolution.ru/",
    "_________________Войти_______________": "https://habr.com/kek/v1/auth/habrahabr/?back=/ru/company/tssolution/blog/495280/&hl=ru",
    "_________________Регистрация_______________": "https://habr.com/kek/v1/auth/habrahabr-register/?back=/ru/company/tssolution/blog/495280/&hl=ru",
    "_________________Публикации_______________": "https://habr.com/ru/",
    "_________________Новости_______________": "https://habr.com/ru/news/",
    "_________________Хабы_______________": "https://habr.com/ru/hubs/",
    "_________________Компании_______________": "https://habr.com/ru/companies/",
    "_________________Авторы_______________": "https://habr.com/ru/users/",
    "_________________Песочница_______________": "https://habr.com/ru/sandbox/",
    "_________________Устройство_сайта_______________": "https://habr.com/ru/docs/help/",
    "_________________Для_авторов_______________": "https://habr.com/ru/docs/authors/codex/",
    "_________________Для_компаний_______________": "https://habr.com/ru/docs/companies/corpblogs/",
    "_________________Документы_______________": "https://habr.com/ru/docs/docs/transparency/",
    "_________________Соглашение_______________": "https://account.habr.com/info/agreement",
    "_________________Конфиденциальность_______________": "https://account.habr.com/info/confidential/",
    "_________________Корпоративный_блог_______________": "https://company.habr.com/ru/corporate-blogs/",
    "_________________Медийная_реклама_______________": "https://company.habr.com/ru/advertising/",
    "_________________Нативные_проекты_______________": "https://company.habr.com/ru/native-special/",
    "_________________Образовательные_программы_______________": "https://company.habr.com/ru/education-programs/",
    "_________________Стартапам_______________": "https://company.habr.com/ru/hello-startup/",
    "_________________Мегапроекты_______________": "https://habr.com/ru/megaprojects/",
    "Facebook_": "https://www.facebook.com/habrahabr.ru",
    "Twitter_": "https://twitter.com/habr_com",
    "VK_": "https://vk.com/habr",
    "Telegram_": "https://telegram.me/habr_com",
    "Youtube_": "https://www.youtube.com/channel/UCd_sTwKqVrweTt4oAKY5y4w",
    "Яндекс_Дзен_": "https://zen.yandex.ru/habr",
    "_________Техническая_поддержка_______": "https://habr.com/ru/feedback/",
    "_________Вернуться_на_старую_версию_______": "https://habr.com/berserk-mode-nope",
    "Habr": "https://company.habr.com/"
}